{
  "id": "add-tool-plugin-b481681e",
  "name": "add-tool-plugin",
  "description": "Add support for a new AI coding tool",
  "repo_url": "https://github.com/krystianjonca/lnai",
  "source_hub": "skillsmp",
  "skill_type": "agent_skill",
  "owner": "krystianjonca",
  "stars": 0,
  "primary_language": "unknown",
  "tags": [
    "agent-skills",
    "data-ai",
    "installs:228"
  ],
  "verification_status": "pass",
  "overall_score": 60,
  "risk_level": "medium",
  "verified_commit": "c43fa8fae33044c0ea54184f399c44e51b42ec99",
  "scan_summary": null,
  "scan_date": "2026-03-04T19:52:53Z",
  "verification_level": "full_pipeline"
}