{
  "id": "ask-21f7eb01",
  "name": "ask",
  "description": "Fast vault Q&A — quick lookups, decision history, blocker status, doc search. Uses QMD hybrid search when available, falls back to vault grep. Use for \"/ask what did we decide about auth?\" or \"/ask who's blocked?\".",
  "repo_url": "https://github.com/kv0906/pm-kit",
  "source_hub": "skillsmp",
  "skill_type": "agent_skill",
  "owner": "kv0906",
  "stars": 0,
  "primary_language": "unknown",
  "tags": [
    "agent-skills",
    "utilities",
    "installs:40"
  ],
  "verification_status": "unverified",
  "overall_score": 0,
  "risk_level": "info",
  "verified_commit": null,
  "scan_summary": null,
  "repo_status": "available",
  "repo_check_date": "2026-03-04T15:09:49.909986+00:00",
  "repo_check_error": null
}