{
  "id": "avant-garde-frontend-architect-60aab824",
  "name": "avant-garde-frontend-architect",
  "description": "Expert frontend design and UI implementation with a focus on bespoke, visually striking, and minimalist interfaces. Trigger with 'ULTRATHINK' prefix for deep architectural analysis. Automatically detects and uses existing UI libraries (Shadcn UI, Radix, MUI) while applying unique styling. Includes a personalized component library system for reusable cross-project elements.",
  "repo_url": "https://github.com/aegntic/cldcde",
  "source_hub": "skillsmp",
  "skill_type": "agent_skill",
  "owner": "aegntic",
  "stars": 0,
  "primary_language": "unknown",
  "tags": [
    "agent-skills",
    "installs:9",
    "dev",
    "dev-web",
    "dev-web-frontend",
    "prod"
  ],
  "verification_status": "unverified",
  "overall_score": 0,
  "risk_level": "info",
  "verified_commit": null,
  "scan_summary": null,
  "repo_status": "available",
  "repo_check_date": "2026-03-04T15:09:49.909986+00:00",
  "repo_check_error": null,
  "installs": 9
}