{
  "id": "ccg-workflow-03e3e2f2",
  "name": "ccg-workflow",
  "description": "CCG (Coder-Codex-Gemini) collaboration for code and document tasks.\nUse when: writing/modifying code, editing documents, implementing features, fixing bugs, refactoring, or code review.\n\u534f\u8c03 Coder \u6267\u884c\u4ee3\u7801/\u6587\u6863\u6539\u52a8\uff0cCodex \u5ba1\u6838\u4ee3\u7801\u8d28\u91cf\u3002",
  "repo_url": "https://github.com/fredericmn/coder-codex-gemini",
  "source_hub": "skillsmp",
  "skill_type": "agent_skill",
  "owner": "fredericmn",
  "stars": 0,
  "primary_language": "unknown",
  "tags": [
    "agent-skills",
    "installs:146"
  ],
  "verification_status": "unverified",
  "overall_score": 0,
  "risk_level": "info",
  "verified_commit": null,
  "scan_summary": null
}