{
  "id": "changelog-9e8f9474",
  "name": "changelog",
  "description": "Maintains IdeaVim changelog (CHANGES.md) and build.gradle.kts changeNotes. Use when updating changelog, documenting releases, or reviewing commits/PRs for changelog entries.",
  "repo_url": "https://github.com/jetbrains/ideavim",
  "source_hub": "skillsmp",
  "skill_type": "agent_skill",
  "owner": "jetbrains",
  "stars": 0,
  "primary_language": "unknown",
  "tags": [
    "agent-skills",
    "dev-web-frontend",
    "installs:10138"
  ],
  "verification_status": "pass",
  "overall_score": 83,
  "risk_level": "medium",
  "verified_commit": "3492e09c49dada687f2943c9c2760850a0e0e290",
  "scan_summary": null,
  "scan_date": "2026-03-05T03:06:35Z",
  "verification_level": "full_pipeline"
}