{
  "id": "chat-nextjs-mcp-client-2b457ba2",
  "name": "chat-nextjs-mcp-client",
  "description": "\u26a1 Chat MCP Client for Remote hosted MCP Servers (with Composio) and locally hosted MCP servers. \ud83d\udce1",
  "repo_url": "https://github.com/shricodev/chat-nextjs-mcp-client",
  "source_hub": "mcp_so",
  "owner": "shricodev",
  "stars": 34,
  "primary_language": "unknown",
  "tags": [
    "dev-web-frontend-react",
    "dev-web-fullstack-nextjs",
    "prod-comm"
  ],
  "verification_status": "pass",
  "overall_score": 85,
  "risk_level": "info",
  "verified_commit": "caefe811ecffeb526723cd894cc2d74e9be85d2c",
  "scan_summary": {
    "total_findings": 0,
    "files_scanned": 20,
    "severity_counts": {},
    "category_counts": {}
  },
  "scan_date": "2026-02-28T03:32:11Z",
  "verification_level": "scanner_only"
}