{
  "id": "context-daemon-944c97ee",
  "name": "context-daemon",
  "description": "An opinionated product development pipeline for builders who use AI agents.",
  "repo_url": "https://github.com/narainio/context-daemon",
  "source_hub": "github_search",
  "skill_type": "agent_skill",
  "owner": "narainio",
  "stars": 0,
  "license": "apache-2.0",
  "primary_language": "markdown",
  "tags": [],
  "verification_status": "unverified",
  "overall_score": 0,
  "risk_level": "info",
  "verified_commit": null,
  "scan_summary": null,
  "last_updated": "2026-03-02T07:45:39Z"
}