{
  "id": "content-fact-check-article-690c86cb",
  "name": "content-fact-check-article",
  "description": "Perform thorough fact-checking of an article against authoritative official sources. Use when user asks to verify facts, check article accuracy, or validate claims before publication.",
  "repo_url": "https://github.com/v112263/it-autonomos-spain",
  "source_hub": "skillsmp",
  "skill_type": "agent_skill",
  "owner": "v112263",
  "stars": 0,
  "primary_language": "unknown",
  "tags": [
    "agent-skills",
    "dev-devops",
    "installs:221"
  ],
  "verification_status": "unverified",
  "overall_score": 0,
  "risk_level": "info",
  "verified_commit": null,
  "scan_summary": null
}