{
  "id": "feed-mcp-622e9c55",
  "name": "feed-mcp",
  "description": "MCP Server for RSS, Atom, and JSON Feeds",
  "repo_url": "https://github.com/richardwooding/feed-mcp",
  "source_hub": "mcp_so",
  "skill_type": "mcp_server",
  "owner": "richardwooding",
  "stars": 14,
  "primary_language": "unknown",
  "tags": [
    "integ",
    "util"
  ],
  "verification_status": "pass",
  "overall_score": 86,
  "risk_level": "medium",
  "verified_commit": "d1c8c6902a8013d1f411baec4298fe19995c7f18",
  "scan_summary": {
    "total_findings": 0,
    "files_scanned": 10,
    "severity_counts": {},
    "category_counts": {}
  },
  "scan_date": "2026-03-03T17:34:51Z",
  "verification_level": "full_pipeline"
}