{
  "id": "gc-safe-coding-540b0bcc",
  "name": "gc-safe-coding",
  "description": "Rules for writing and reviewing GC-safe C++ code in the Hermes VM runtime. Use when writing, modifying, or reviewing C++ runtime VM code that uses internal Hermes VM APIs (as opposed to code using JSI). This includes working with GC-managed types (HermesValue, Handle, PinnedValue, JSObject, StringPrimitive, etc.), Locals, GCScope, PseudoHandle, CallResult, or any function with _RJS suffix. Typically in lib/VM/, include/hermes/VM/, or API/hermes/.",
  "repo_url": "https://github.com/facebook/hermes",
  "source_hub": "skillsmp",
  "skill_type": "agent_skill",
  "owner": "facebook",
  "stars": 0,
  "primary_language": "unknown",
  "tags": [
    "agent-skills",
    "dev-web-backend",
    "installs:10798"
  ],
  "verification_status": "pass",
  "overall_score": 50,
  "risk_level": "medium",
  "verified_commit": "0239ec8cc73cf3bfbf0c956f7fa78462af3687dc",
  "scan_summary": null,
  "scan_date": "2026-03-05T03:06:18Z",
  "verification_level": "full_pipeline"
}