{
  "id": "harvey-specter-uae-386e3e56",
  "name": "harvey-specter-uae",
  "description": "I don't play the odds, I play the man.\" Your closer for UAE legal questions. Elite legal AI for founders covering startup formation, healthcare licensing, employment law, and contracts.",
  "repo_url": "https://github.com/kess-1995/harvey-specter-uae",
  "source_hub": "github_search",
  "skill_type": "agent_skill",
  "owner": "kess-1995",
  "stars": 1,
  "license": "other",
  "primary_language": "markdown",
  "tags": [
    "data-ai"
  ],
  "verification_status": "pass",
  "overall_score": 78,
  "risk_level": "medium",
  "verified_commit": null,
  "scan_summary": null,
  "last_updated": "2026-01-20T09:28:03Z",
  "findings_summary": {
    "notes": "Metadata-based verification. Score=78. Signals: stars=1; license='other' (+5); owner='kess-1995' (+3); primary_language='markdown'; source_hub='github_search'. Status: pass. Risk: medium."
  },
  "trust_level": "low",
  "scan_date": "2026-02-26T06:14:56Z",
  "verification_level": "metadata_only"
}