{
  "id": "image-downloader-84bde208",
  "name": "image-downloader",
  "description": "\u4e00\u4e2a\u652f\u6301\u56fe\u7247\u4e0b\u8f7d\u548c\u5904\u7406\u7684 MCP (Model Context Protocol) \u670d\u52a1\u5668\uff0c\u5177\u6709\u8fdb\u5ea6\u8ddf\u8e2a\u3001\u6279\u91cf\u4e0b\u8f7d\u548c\u56fe\u7247\u5904\u7406\u529f\u80fd\u3002",
  "repo_url": "https://github.com/yekyos/image-downloader",
  "source_hub": "mcp_so",
  "owner": "yekyos",
  "stars": 0,
  "primary_language": "unknown",
  "tags": [
    "repo_unavailable",
    "data-ai",
    "data-ai-nlp",
    "data-ai-vision",
    "util-file"
  ],
  "verification_status": "unverified",
  "overall_score": 0,
  "risk_level": "info",
  "verified_commit": null,
  "scan_summary": null,
  "repo_status": "unavailable",
  "repo_check_date": "2026-02-28T20:51:51.262755+00:00",
  "repo_check_error": "fatal: could not read Username for 'https://github.com': Device not configured"
}