{
  "id": "juniors-best-practice-0fb94cac",
  "name": "juniors-best-practice",
  "description": "Juniors-focused React and TypeScript best practices. Use this skill when writing or reviewing code to enforce clear, consistent, and maintainable patterns across common scopes like React, TypeScript, styling, devtools, assets, and Git.",
  "repo_url": "https://github.com/siberiacancode/agent-skills",
  "source_hub": "skillsmp",
  "skill_type": "agent_skill",
  "owner": "siberiacancode",
  "stars": 0,
  "primary_language": "unknown",
  "tags": [
    "agent-skills",
    "dev-web-frontend",
    "installs:11"
  ],
  "verification_status": "unverified",
  "overall_score": 0,
  "risk_level": "info",
  "verified_commit": null,
  "scan_summary": null
}