{
  "id": "linkedin-mcp-c055ce57",
  "name": "linkedin-mcp",
  "description": "A MCP server for LinkedIn to seamlessly apply for jobs\ud83d\ude80",
  "repo_url": "https://github.com/Hritik003/linkedin-mcp",
  "source_hub": "mcp_so",
  "skill_type": "mcp_server",
  "owner": "Hritik003",
  "stars": 29,
  "primary_language": "unknown",
  "tags": [
    "integ",
    "integ-social"
  ],
  "verification_status": "pass",
  "overall_score": 98,
  "risk_level": "medium",
  "verified_commit": "cb22a465bb75cd93199747c073c9aba20baadb3a",
  "scan_summary": {
    "total_findings": 0,
    "files_scanned": 4,
    "severity_counts": {},
    "category_counts": {}
  },
  "scan_date": "2026-03-03T15:02:23Z",
  "verification_level": "full_pipeline"
}