{
  "id": "mcp-gateway-00720b0a",
  "name": "mcp-gateway",
  "description": "A plugin-based gateway that orchestrates other MCPs and allows developers to build upon it enterprise-grade agents.",
  "repo_url": "https://github.com/lasso-security/mcp-gateway",
  "source_hub": "mcp_so",
  "owner": "lasso-security",
  "stars": 347,
  "primary_language": "unknown",
  "tags": [
    "dev"
  ],
  "verification_status": "pass",
  "overall_score": 85,
  "risk_level": "info",
  "verified_commit": null,
  "scan_summary": {
    "total_findings": 0,
    "files_scanned": 36,
    "severity_counts": {},
    "category_counts": {}
  },
  "scan_date": "2026-02-27T02:28:45Z",
  "verification_level": "scanner_only"
}
