{
  "id": "mcp-wikipedia-e87096ed",
  "name": "mcp-wikipedia",
  "description": "A simple MCP Server in Python for working with Wikipedia topic content in a GenAI context",
  "repo_url": "https://github.com/danbunnell/mcp-wikipedia",
  "source_hub": "mcp_so",
  "skill_type": "mcp_server",
  "owner": "danbunnell",
  "stars": 1,
  "primary_language": "unknown",
  "tags": [
    "dev",
    "dev-web",
    "dev-web-backend",
    "dev-web-backend-python"
  ],
  "verification_status": "pass",
  "overall_score": 93,
  "risk_level": "medium",
  "verified_commit": "6e27d402a89b508c795f435aef53280059ce5040",
  "scan_summary": {
    "total_findings": 0,
    "files_scanned": 4,
    "severity_counts": {},
    "category_counts": {}
  },
  "scan_date": "2026-03-03T20:51:33Z",
  "verification_level": "full_pipeline"
}