{
  "id": "mcp-deno-sandbox-e0c942fb",
  "name": "mcp-deno-sandbox",
  "description": "An MCP server that allows you to run TypeScript, JavaScript, and Python code in a sandbox on your local machine using the Deno\u00ae sandbox. This server provides a controlled environment for executing code with explicit permission controls.",
  "repo_url": "https://github.com/bewt85/mcp-deno-sandbox",
  "source_hub": "mcp_so",
  "skill_type": "mcp_server",
  "owner": "bewt85",
  "stars": 13,
  "primary_language": "unknown",
  "tags": [
    "dev",
    "dev-web",
    "dev-web-backend",
    "dev-web-backend-python"
  ],
  "verification_status": "pass",
  "overall_score": 82,
  "risk_level": "medium",
  "verified_commit": "84ec190513e6b7726036a161338197451c6c3144",
  "scan_summary": {
    "total_findings": 0,
    "files_scanned": 11,
    "severity_counts": {},
    "category_counts": {}
  },
  "scan_date": "2026-03-03T17:34:53Z",
  "verification_level": "full_pipeline"
}