{
  "id": "mcp-servers-1186a27f",
  "name": "mcp-servers",
  "description": "Collection of MCP server implementation.",
  "repo_url": "https://github.com/rcw3bb/mcp-servers",
  "source_hub": "mcp_so",
  "owner": "rcw3bb",
  "stars": 0,
  "primary_language": "unknown",
  "tags": [
    "integ",
    "util"
  ],
  "verification_status": "pass",
  "overall_score": 85,
  "risk_level": "info",
  "verified_commit": "338c6fec5986d2e85711892fc9d52d333fb6a083",
  "scan_summary": {
    "total_findings": 0,
    "files_scanned": 65,
    "severity_counts": {},
    "category_counts": {}
  },
  "scan_date": "2026-02-28T04:14:41Z",
  "verification_level": "scanner_only"
}
