{
  "id": "mcp-servers-f9e433f9",
  "name": "mcp-servers",
  "description": "MCP Servers For System",
  "repo_url": "https://github.com/The-System-Coperation/mcp-servers",
  "source_hub": "mcp_so",
  "owner": "The-System-Coperation",
  "stars": 0,
  "primary_language": "unknown",
  "tags": [
    "integ",
    "util"
  ],
  "verification_status": "pass",
  "overall_score": 85,
  "risk_level": "info",
  "verified_commit": "1c238b44a29c9298d722d546941e1ab63bfbd2e7",
  "scan_summary": {
    "total_findings": 0,
    "files_scanned": 64,
    "severity_counts": {},
    "category_counts": {}
  },
  "scan_date": "2026-02-28T04:14:40Z",
  "verification_level": "scanner_only"
}