{
  "id": "microsoft-foundry-54afad5b",
  "name": "Microsoft Foundry",
  "description": "Agent skill: microsoft-foundry from microsoft/azure-skills",
  "repo_url": "https://github.com/microsoft/azure-skills",
  "source_hub": "skills_sh",
  "skill_type": "mcp_server",
  "owner": "microsoft",
  "stars": 19600,
  "primary_language": "unknown",
  "tags": [
    "agent-skill",
    "skills-sh"
  ],
  "verification_status": "unverified",
  "overall_score": 0,
  "risk_level": "info",
  "verified_commit": null,
  "scan_summary": null
}