{
  "id": "newsletter-events-add-source-86c830b3",
  "name": "newsletter-events-add-source",
  "description": "Add Instagram accounts or web aggregators to sources.yaml configuration",
  "repo_url": "https://github.com/aniketpanjwani/local_media_tools",
  "source_hub": "skillsmp",
  "skill_type": "agent_skill",
  "owner": "aniketpanjwani",
  "stars": 0,
  "primary_language": "unknown",
  "tags": [
    "agent-skills",
    "installs:39"
  ],
  "verification_status": "unverified",
  "overall_score": 0,
  "risk_level": "info",
  "verified_commit": null,
  "scan_summary": null
}