{
  "id": "nostr-code-snippet-mcp-b130b16f",
  "name": "nostr-code-snippet-mcp",
  "description": "🤖 code snippet mcp server",
  "repo_url": "https://github.com/nodetec/nostr-code-snippet-mcp",
  "source_hub": "mcp_so",
  "owner": "nodetec",
  "stars": 2,
  "primary_language": "unknown",
  "tags": [
    "dev"
  ],
  "verification_status": "pass",
  "overall_score": 85,
  "risk_level": "info",
  "verified_commit": "14f3208f08597c31c54903900a039b1d3e896d82",
  "scan_summary": {
    "total_findings": 0,
    "files_scanned": 9,
    "severity_counts": {},
    "category_counts": {}
  },
  "scan_date": "2026-02-28T04:04:51Z",
  "verification_level": "scanner_only"
}
