{
  "id": "notion-mcp-1744d172",
  "name": "notion_mcp",
  "description": "MCP Server for Notion",
  "repo_url": "https://github.com/DaleCameron/notion_mcp",
  "source_hub": "mcp_so",
  "owner": "DaleCameron",
  "stars": 0,
  "primary_language": "unknown",
  "tags": [
    "prod-docs"
  ],
  "verification_status": "pass",
  "overall_score": 85,
  "risk_level": "info",
  "verified_commit": "bf28bb87838b5864ffcf506a0e69b7f4c900692c",
  "scan_summary": {
    "total_findings": 0,
    "files_scanned": 1,
    "severity_counts": {},
    "category_counts": {}
  },
  "scan_date": "2026-02-28T04:14:41Z",
  "verification_level": "scanner_only"
}
