{
  "id": "octagon-sec-filings-mcp-4f84666c",
  "name": "octagon-sec-filings-mcp",
  "description": "The Octagon SEC Filings MCP server provides specialized AI-powered SEC filings analysis capabilities by integrating with advanced SEC analysis agents. Covers over 8,000 public companies from SEC EDGAR with comprehensive coverage of annual and quarterly reports, offering filings, amendments, and event filings.",
  "repo_url": "https://github.com/OctagonAI/octagon-sec-filings-mcp",
  "source_hub": "mcp_so",
  "owner": "OctagonAI",
  "stars": 0,
  "primary_language": "unknown",
  "tags": [
    "data-ai"
  ],
  "verification_status": "unverified",
  "overall_score": 85,
  "risk_level": "info",
  "verified_commit": "ce1280a56ec2fe319c9befc0f0ca4223fe63413c",
  "scan_summary": {
    "total_findings": 0,
    "files_scanned": 7,
    "severity_counts": {},
    "category_counts": {}
  },
  "scan_date": "2026-02-28T04:14:42Z",
  "status_cleared": {
    "date": "2026-03-02T20:40:18.531782+00:00",
    "previous_status": "pass",
    "previous_score": 85,
    "previous_risk": "info",
    "verification_level": "scanner_only",
    "reason": "SM cleanup: only full_pipeline pass is real pass. Needs re-verification."
  },
  "skill_type": "mcp_server"
}