{
  "id": "postgres-mcp-d31932ec",
  "name": "postgres-mcp",
  "description": "Postgres MCP server",
  "repo_url": "https://github.com/Tibiritabara/postgres-mcp",
  "source_hub": "mcp_so",
  "owner": "Tibiritabara",
  "stars": 6,
  "primary_language": "unknown",
  "tags": [
    "data-db"
  ],
  "verification_status": "pass",
  "overall_score": 78,
  "risk_level": "low",
  "verified_commit": null,
  "scan_summary": null,
  "scan_date": "2026-02-26T03:00:50Z",
  "verification_level": "scanner_only"
}
