{
  "id": "questionably-ultrathink-c47c2620",
  "name": "questionably-ultrathink",
  "description": "Questionably UltraThink your most complex tasks combining AoT (Atom of Thoughts) and CoV (Chain of Verification)",
  "repo_url": "https://github.com/snowmead/questionably-ultrathink",
  "source_hub": "github_search",
  "skill_type": "agent_skill",
  "owner": "snowmead",
  "stars": 2,
  "license": "",
  "primary_language": "markdown",
  "tags": [
    "data-ai",
    "prod-pm"
  ],
  "verification_status": "pass",
  "overall_score": 73,
  "risk_level": "medium",
  "verified_commit": null,
  "scan_summary": null,
  "last_updated": "2026-02-24T03:02:01Z",
  "findings_summary": {
    "notes": "Metadata-based verification. Score=73. Signals: stars=2; no license detected; owner='snowmead' (+3); primary_language='markdown'; source_hub='github_search'. Status: pass. Risk: medium."
  },
  "trust_level": "low",
  "scan_date": "2026-02-26T06:14:56Z",
  "verification_level": "metadata_only"
}
