{
  "id": "requesting-code-review-2d940c2b",
  "name": "requesting-code-review",
  "description": "Structured code review workflow for SRTD development. Use after implementing features, fixing bugs, or before merging to main. Ensures production-readiness through systematic review.",
  "repo_url": "https://github.com/t1mmen/srtd",
  "source_hub": "skillsmp",
  "skill_type": "agent_skill",
  "owner": "t1mmen",
  "stars": 0,
  "primary_language": "unknown",
  "tags": [
    "agent-skills",
    "installs:103",
    "prod"
  ],
  "verification_status": "unverified",
  "overall_score": 0,
  "risk_level": "info",
  "verified_commit": null,
  "scan_summary": null,
  "repo_status": "available",
  "repo_check_date": "2026-03-04T15:09:49.909986+00:00",
  "repo_check_error": null,
  "installs": 103
}