{
  "id": "sleek-design-mobile-apps-65a2fe19",
  "name": "Sleek Design Mobile Apps",
  "description": "Agent skill: sleek-design-mobile-apps from sleekdotdesign/agent-skills",
  "repo_url": "https://github.com/sleekdotdesign/agent-skills",
  "source_hub": "skills_sh",
  "skill_type": "mcp_server",
  "owner": "sleekdotdesign",
  "stars": 105400,
  "primary_language": "unknown",
  "tags": [
    "agent-skill",
    "skills-sh"
  ],
  "verification_status": "unverified",
  "overall_score": 0,
  "risk_level": "info",
  "verified_commit": null,
  "scan_summary": null
}