{
  "id": "solon-223cc44c",
  "name": "solon",
  "description": "\ud83d\udd25 Java enterprise application development framework for full scenario: Restrained, Efficient, Open, Ecologicalll!!! 700% higher concurrency 50% memory savings Startup is 10 times faster. Packing 90% smaller; Compatible with java8 ~ java24. (Replaceable spring)",
  "repo_url": "https://github.com/opensolon/solon",
  "source_hub": "mcp_so",
  "skill_type": "mcp_server",
  "owner": "opensolon",
  "stars": 2705,
  "primary_language": "unknown",
  "tags": [
    "dev",
    "dev-web",
    "dev-web-backend"
  ],
  "verification_status": "pass",
  "overall_score": 55,
  "risk_level": "medium",
  "verified_commit": "94ab5d74244a6b36aff9182596999709eff4687e",
  "scan_summary": null,
  "scan_date": "2026-03-01T07:24:13Z",
  "verification_level": "full_pipeline"
}