{
  "id": "spring-boot-bitcoin-mcp-server-2025-5aef1f94",
  "name": "spring-boot-bitcoin-mcp-server-2025",
  "description": "A demonstration of A Spring Boot/AI MCP Server that tracks Bitcoin prices using CoinGecko APIs (api.coingecko.com/api/v3)",
  "repo_url": "https://github.com/nlinhvu/spring-boot-bitcoin-mcp-server-2025",
  "source_hub": "mcp_so",
  "skill_type": "mcp_server",
  "owner": "nlinhvu",
  "stars": 0,
  "primary_language": "unknown",
  "tags": [],
  "verification_status": "unverified",
  "overall_score": 0,
  "risk_level": "info",
  "verified_commit": null,
  "scan_summary": null
}