{
  "id": "tiptap-6e0289e5",
  "name": "tiptap",
  "description": "Build rich text editors with Tiptap - headless editor framework with React and Tailwind v4. Covers SSR-safe setup, image uploads, prose styling, and collaborative editing.\n\nUse when creating blog editors, comment systems, or Notion-like apps, or troubleshooting SSR hydration errors, typography issues, or image upload problems.",
  "repo_url": "https://github.com/mhl5/mhl5.vercel.app",
  "source_hub": "skillsmp",
  "skill_type": "agent_skill",
  "owner": "mhl5",
  "stars": 0,
  "primary_language": "unknown",
  "tags": [
    "agent-skills",
    "installs:17",
    "dev",
    "dev-web",
    "dev-web-frontend",
    "dev-web-frontend-react",
    "integ",
    "integrations-notion",
    "prod",
    "prod-docs"
  ],
  "verification_status": "unverified",
  "overall_score": 0,
  "risk_level": "info",
  "verified_commit": null,
  "scan_summary": null,
  "repo_status": "available",
  "repo_check_date": "2026-03-04T15:09:49.909986+00:00",
  "repo_check_error": null
}