{
  "id": "victoriametrics-mcp-server-d809805b",
  "name": "VictoriaMetrics-mcp-server",
  "description": "MCP Server for the VictoriaMetrics.",
  "repo_url": "https://github.com/yincongcyincong/VictoriaMetrics-mcp-server",
  "source_hub": "mcp_so",
  "skill_type": "mcp_server",
  "owner": "yincongcyincong",
  "stars": 7,
  "primary_language": "unknown",
  "tags": [
    "integ",
    "util"
  ],
  "verification_status": "pass",
  "overall_score": 83,
  "risk_level": "medium",
  "verified_commit": "c3a5ef928875f627f39cbd24d250a402cd3f7079",
  "scan_summary": {
    "total_findings": 0,
    "files_scanned": 5,
    "severity_counts": {},
    "category_counts": {}
  },
  "scan_date": "2026-03-03T17:49:40Z",
  "verification_level": "full_pipeline"
}