{
  "id": "websocket-mcp-5ac5079f",
  "name": "websocket_mcp",
  "description": "Model Context Protocol (MCP) server and client with a custom websocket transport layer.",
  "repo_url": "https://github.com/zeropointo/websocket_mcp",
  "source_hub": "mcp_so",
  "owner": "zeropointo",
  "stars": 0,
  "primary_language": "unknown",
  "tags": [
    "repo_unavailable",
    "integ",
    "util"
  ],
  "verification_status": "unverified",
  "overall_score": 0,
  "risk_level": "info",
  "verified_commit": null,
  "scan_summary": null,
  "repo_status": "unavailable",
  "repo_check_date": "2026-02-28T20:53:08.621768+00:00",
  "repo_check_error": "fatal: could not read Username for 'https://github.com': Device not configured",
  "skill_type": "mcp_server"
}