{
  "started_at": "2026-02-28T22:41:16Z",
  "finished_at": "2026-02-28T22:41:32Z",
  "skill_type": "mcp_server",
  "selected_ids": [
    "mkinf-44a82af2",
    "mcp-redmine-ceedfb5e",
    "crawl4ai-mcp-server-ada574fb",
    "isaac-sim-mcp-36d9be7b",
    "mcp-client-server-b4b233a2",
    "portainer-mcp-666cb919",
    "polymarket-mcp-2233f580",
    "mcppserver-de7492c5",
    "cli-75f2cd30",
    "rat-retrieval-augmented-thinking-mcp-5df7133d"
  ],
  "selected_count": 10,
  "group_count": 5,
  "processed_count": 10,
  "status_counts": {
    "pass": 5,
    "manual_review": 4,
    "fail": 1
  },
  "stage_failures": {},
  "retry_ids": [],
  "remaining_unverified": 0
}
